Metadata-Version: 2.1
Name: bmg-sms-gateway
Version: 0.0.9
Summary: A package to assist with bmg sms gateway integrations in python
Home-page: https://github.com/RONALD55/BMG-SMS-GATEWAY
Author: Ronald Nyasha Kanyepi
Author-email: kanyepironald@gmail.com
License: MIT
Keywords: zimbabwe,sms in Zimbabwe,bulk messages zimbabwe,sms gateway for Zim numbers
Platform: UNKNOWN
Classifier: Development Status :: 5 - Production/Stable
Classifier: Intended Audience :: Education
Classifier: Intended Audience :: Developers
Classifier: Operating System :: Microsoft :: Windows :: Windows 10
Classifier: License :: OSI Approved :: MIT License
Classifier: Programming Language :: Python :: 3
